weallcode_robot/__init__.py
weallcode_robot/commands.py
weallcode_robot/robot.py
weallcode_robot/robot_ui.py
weallcode_robot/robotapp.py
weallcode_robot/utils.py
weallcode_robot-3.1.4.dist-info/METADATA
weallcode_robot-3.1.4.dist-info/WHEEL
weallcode_robot-3.1.4.dist-info/RECORD
