Metadata-Version: 2.1
Name: weallcode_robot
Version: 3.1.4
Summary: Micro:bit TinyBit BLE Python Library
Home-page: https://github.com/WeAllCode/tinybit-python
License: MIT
Author: Blaine Rothrock
Author-email: blaine.p.rothrock@gmail.com
Requires-Python: >=3.11,<4.0
Classifier: Development Status :: 4 - Beta
Classifier: License :: OSI Approved :: MIT License
Classifier: Programming Language :: Python
Classifier: Programming Language :: Python :: 3
Classifier: Programming Language :: Python :: 3.11
Classifier: Programming Language :: Python :: 3.12
Classifier: Programming Language :: Python :: 3.13
Classifier: Programming Language :: Python :: 3 :: Only
Classifier: Programming Language :: Python :: 3.10
Classifier: Programming Language :: Python :: 3.4
Classifier: Programming Language :: Python :: 3.5
Classifier: Programming Language :: Python :: 3.6
Classifier: Programming Language :: Python :: 3.7
Classifier: Programming Language :: Python :: 3.8
Classifier: Programming Language :: Python :: 3.9
Requires-Dist: bleak (>=0.20.1,<0.21.0)
Requires-Dist: textual (>=0.71.0,<0.72.0)
Project-URL: Repository, https://github.com/WeAllCode/tinybit-python
